{
  "updatedAt": "2026-06-16T23:22:40.058Z",
  "source": "football-data.org",
  "results": {
    "M1": {
      "homeGoals": 2,
      "awayGoals": 0,
      "status": "FINISHED"
    },
    "M2": {
      "homeGoals": 2,
      "awayGoals": 1,
      "status": "FINISHED"
    },
    "M3": {
      "homeGoals": 1,
      "awayGoals": 1,
      "status": "FINISHED"
    },
    "M4": {
      "homeGoals": 4,
      "awayGoals": 1,
      "status": "FINISHED"
    },
    "M8": {
      "homeGoals": 1,
      "awayGoals": 1,
      "status": "FINISHED"
    },
    "M7": {
      "homeGoals": 1,
      "awayGoals": 1,
      "status": "FINISHED"
    },
    "M5": {
      "homeGoals": 0,
      "awayGoals": 1,
      "status": "FINISHED"
    },
    "M6": {
      "homeGoals": 2,
      "awayGoals": 0,
      "status": "FINISHED"
    },
    "M10": {
      "homeGoals": 7,
      "awayGoals": 1,
      "status": "FINISHED"
    },
    "M11": {
      "homeGoals": 2,
      "awayGoals": 2,
      "status": "FINISHED"
    },
    "M9": {
      "homeGoals": 1,
      "awayGoals": 0,
      "status": "FINISHED"
    },
    "M12": {
      "homeGoals": 5,
      "awayGoals": 1,
      "status": "FINISHED"
    },
    "M14": {
      "homeGoals": 0,
      "awayGoals": 0,
      "status": "FINISHED"
    },
    "M16": {
      "homeGoals": 1,
      "awayGoals": 1,
      "status": "FINISHED"
    },
    "M13": {
      "homeGoals": 1,
      "awayGoals": 1,
      "status": "FINISHED"
    },
    "M15": {
      "homeGoals": 2,
      "awayGoals": 2,
      "status": "FINISHED"
    },
    "M17": {
      "homeGoals": 3,
      "awayGoals": 1,
      "status": "FINISHED"
    },
    "M18": {
      "homeGoals": 1,
      "awayGoals": 2,
      "status": "IN_PLAY"
    }
  }
}
